asyyclients/__init__.py
asyyclients/yclients.py
asyyclients-0.0.1.1.dist-info/LICENSE
asyyclients-0.0.1.1.dist-info/METADATA
asyyclients-0.0.1.1.dist-info/WHEEL
asyyclients-0.0.1.1.dist-info/top_level.txt
asyyclients-0.0.1.1.dist-info/RECORD
