Metadata-Version: 2.1
Name: asyyclients
Version: 0.0.1.1
Summary: Python asynchronous YCLIENTS REST API wrapper on ujson and httpx
Home-page: https://github.com/barabum0/asyyclients
Author: Roman Poltorabatko
Author-email: barabum@duck.com
License: MIT
Project-URL: Bug Tracker, https://github.com/barabum0/asyyclients/issues
Keywords: yclients,api,wrapper,python,httpx,ujson,async,asyncio,asynchronous
Platform: any
Classifier: Intended Audience :: Developers
Classifier: License :: OSI Approved :: MIT License
Classifier: Operating System :: OS Independent
Classifier: Programming Language :: Python
Classifier: Programming Language :: Python :: 3.7
Classifier: Programming Language :: Python :: 3.8
Classifier: Programming Language :: Python :: 3.9
Classifier: Programming Language :: Python :: 3.10
Classifier: Programming Language :: Python :: 3.11
Classifier: Topic :: Software Development :: Libraries :: Python Modules
Requires-Python: >=3.7
License-File: LICENSE
